ci.py
aws_lambda_ci-0.0.8.dist-info/LICENSE
aws_lambda_ci-0.0.8.dist-info/METADATA
aws_lambda_ci-0.0.8.dist-info/WHEEL
aws_lambda_ci-0.0.8.dist-info/entry_points.txt
aws_lambda_ci-0.0.8.dist-info/top_level.txt
aws_lambda_ci-0.0.8.dist-info/RECORD
