Metadata-Version: 2.1
Name: aws-lambda-ci
Version: 0.0.8
Summary: Continuous integration pipeline for aws lambda function
Home-page: https://github.com/kodless/aws-lambda-ci
Author: Hamza Adami
Author-email: me@adamihamza.com
License: Apache License 2.0
Keywords: aws,lambda,ci,cd,serverless
Platform: any
Requires-Python: >=3.6
License-File: LICENSE
Requires-Dist: boto3
Requires-Dist: awslogs
